neurol/BCI.py
neurol/BCI_tools.py
neurol/__init__.py
neurol/connect_device.py
neurol/plot.py
neurol/streams.py
neurol/models/__init__.py
neurol/models/blink_balanced-recall.h5
neurol/models/blink_balanced.h5
neurol/models/blink_recall.h5
neurol/models/classification_tools.py
neurol/models/data_exploration.py
neurol/models/model_tools.py
neurol/models/preprocessing.py
neurol-0.0.5.dist-info/LICENSE
neurol-0.0.5.dist-info/METADATA
neurol-0.0.5.dist-info/WHEEL
neurol-0.0.5.dist-info/top_level.txt
neurol-0.0.5.dist-info/RECORD
