Metadata-Version: 2.1
Name: neurol
Version: 0.0.5
Summary: A package for modularly implenting Brain-Computer Interfaces
Home-page: https://github.com/Awni00/neurol
Author: Awni
Author-email: awni.altabaa@queensu.ca
License: UNKNOWN
Project-URL: Documentation, https://neurol.readthedocs.io/
Project-URL: Source, https://github.com/Awni00/neurol
Project-URL: Tracker, https://github.com/Awni00/neurol/issues
Keywords: BCI Brain-Computer Interface Neurotechnology Neuroscience EEG
Platform: UNKNOWN
Classifier: Development Status :: 3 - Alpha
Classifier: Programming Language :: Python :: 3
Classifier: License :: OSI Approved :: MIT License
Classifier: Operating System :: OS Independent
Requires-Python: >=3.6
Requires-Dist: numpy
Requires-Dist: pylsl
Requires-Dist: scipy
